deepgnn/__init__.py
deepgnn/arg_types.py
deepgnn/log_consts.py
deepgnn/logging_utils.py
deepgnn/train_types.py
deepgnn/pytorch/__init__.py
deepgnn/pytorch/common/__init__.py
deepgnn/pytorch/common/aggregators.py
deepgnn/pytorch/common/args.py
deepgnn/pytorch/common/consts.py
deepgnn/pytorch/common/dataset.py
deepgnn/pytorch/common/metrics.py
deepgnn/pytorch/common/optimization.py
deepgnn/pytorch/common/test_metrics.py
deepgnn/pytorch/common/test_utils.py
deepgnn/pytorch/common/utils.py
deepgnn/pytorch/encoding/__init__.py
deepgnn/pytorch/encoding/feature_encoder.py
deepgnn/pytorch/encoding/gnn_encoder_gat.py
deepgnn/pytorch/encoding/gnn_encoder_hetgnn.py
deepgnn/pytorch/encoding/gnn_encoder_lgcl.py
deepgnn/pytorch/encoding/gnn_encoder_lightgcn.py
deepgnn/pytorch/encoding/gnn_encoder_sage.py
deepgnn/pytorch/encoding/test_feature_encoder.py
deepgnn/pytorch/encoding/test_gnn_encoders.py
deepgnn/pytorch/encoding/twinbert/__init__.py
deepgnn/pytorch/encoding/twinbert/configuration.py
deepgnn/pytorch/encoding/twinbert/embedding.py
deepgnn/pytorch/encoding/twinbert/encoder.py
deepgnn/pytorch/encoding/twinbert/pooler.py
deepgnn/pytorch/encoding/twinbert/test_encoder.py
deepgnn/pytorch/encoding/twinbert/test_tokenization.py
deepgnn/pytorch/encoding/twinbert/tokenization.py
deepgnn/pytorch/encoding/twinbert/deepspeed/__init__.py
deepgnn/pytorch/encoding/twinbert/deepspeed/convert_bert_ckpt_to_deepspeed.py
deepgnn/pytorch/encoding/twinbert/deepspeed/file_utils.py
deepgnn/pytorch/encoding/twinbert/deepspeed/loss.py
deepgnn/pytorch/encoding/twinbert/deepspeed/nvidia_modeling.py
deepgnn/pytorch/encoding/twinbert/deepspeed/nvidia_modeling_no_apex.py
deepgnn/pytorch/modeling/__init__.py
deepgnn/pytorch/modeling/base_model.py
deepgnn/pytorch/nn/__init__.py
deepgnn/pytorch/nn/gat_conv.py
deepgnn/pytorch/nn/test_conv.py
deepgnn/pytorch/training/__init__.py
deepgnn/pytorch/training/args.py
deepgnn/pytorch/training/factory.py
deepgnn/pytorch/training/test_trainer.py
deepgnn_torch-0.1.60.dist-info/METADATA
deepgnn_torch-0.1.60.dist-info/WHEEL
deepgnn_torch-0.1.60.dist-info/top_level.txt
deepgnn_torch-0.1.60.dist-info/RECORD
