Metadata-Version: 2.1
Name: deepgnn-torch
Version: 0.1.60
Summary: DeepGNN algorithms for pytorch.
Home-page: https://github.com/microsoft/DeepGNN
Author: DeepGNN Team
Author-email: DeepGNN@microsoft.com
License: MIT
Classifier: Development Status :: 3 - Alpha
Classifier: Intended Audience :: Developers
Classifier: Intended Audience :: Science/Research
Classifier: License :: OSI Approved :: MIT License
Classifier: Programming Language :: Python :: 3
Classifier: Programming Language :: Python :: 3.7
Classifier: Programming Language :: Python :: 3.8
Classifier: Programming Language :: Python :: 3.9
Classifier: Programming Language :: Python :: 3.10
Classifier: Topic :: Scientific/Engineering
Classifier: Topic :: Software Development :: Libraries
Requires-Python: >=3.7
Requires-Dist: deepgnn-ge (>=0.1)
Requires-Dist: torch (>=1.8)
Requires-Dist: boto3 (>=1.15.16)
Requires-Dist: transformers (>=4.3.3)
Requires-Dist: sentencepiece (>=0.1.95)
Requires-Dist: tqdm (>=4.51.0)
Requires-Dist: requests
Requires-Dist: tensorboard
